{
  "$schema": "https://zed.dev/schema/themes/v0.2.0.json",
  "name": "Vajra Eclipse",
  "author": "Jon Bodnar",
  "themes": [
    {
      "name": "Vajra Eclipse",
      "appearance": "dark",
      "description": "A deep oceanic variation of the Vajra family. Cool blue-grays meet mint greens and coral pinks for a moody, eclipse-inspired coding experience. Fully WCAG AA compliant with optimized contrast.",
      "keywords": [
        "eclipse",
        "oceanic",
        "dark",
        "vajra",
        "moody",
        "cool",
        "mint",
        "coral",
        "accessibility"
      ],
      "version": "1.0.0",
      "style": {
        "background": "#0f131aff",
        "surface.background": "#151c26ff",
        "elevated_surface.background": "#1d2532ff",
        "panel.background": "#0f131aff",
        "editor.background": "#151c26ff",
        "editor.gutter.background": "#151c26ff",
        "editor.subheader.background": "#0f131aff",
        "editor.foreground": "#d0d8e5ff",
        "editor.line_number": "#7a8fa5ff",
        "editor.active_line_number": "#99e6ffff",
        "editor.active_line.background": "#4fc1e90f",
        "editor.highlighted_line.background": "#4fc1e91a",
        "editor.invisible": "#55667a99",
        "editor.wrap_guide": "#55667a80",
        "editor.active_wrap_guide": "#6b7f96cc",
        "editor.indent_guide": "#55667a80",
        "editor.indent_guide_active": "#7a8fa566",
        "editor.document_highlight.read_background": "#4fc1e91a",
        "editor.document_highlight.write_background": "#ff9eb533",
        "editor.document_highlight.bracket_background": "#55667a44",
        "editor.selection": "#4fc1e933",
        "editor.selection.border": "#4fc1e900",
        "editor.selection.highlight": "#4fc1e944",
        "editor.selection.highlight.border": "#4fc1e900",
        "editor.whitespace": "#55667a66",
        "editor.ruler": "#1d2532ff",
        "editor.focused_border": "#99e6ffcc",
        "editor.hover_line_number": "#99e6ffff",

        "terminal.background": "#0f131aff",
        "terminal.foreground": "#d0d8e5ff",
        "terminal.bright_foreground": "#f0f4f8ff",
        "terminal.dim_foreground": "#8fa3b9ff",
        "terminal.ansi.black": "#0f131aff",
        "terminal.ansi.bright_black": "#5c6e83ff",
        "terminal.ansi.red": "#ff8595ff",
        "terminal.ansi.bright_red": "#ff9eb5ff",
        "terminal.ansi.green": "#b3f5d7ff",
        "terminal.ansi.bright_green": "#c5ffe3ff",
        "terminal.ansi.yellow": "#e0c78aff",
        "terminal.ansi.bright_yellow": "#f0d7a5ff",
        "terminal.ansi.blue": "#4fc1e9ff",
        "terminal.ansi.bright_blue": "#6bcdf9ff",
        "terminal.ansi.magenta": "#bda6ffff",
        "terminal.ansi.bright_magenta": "#d0bbffff",
        "terminal.ansi.cyan": "#99e6ffff",
        "terminal.ansi.bright_cyan": "#aaf0ffff",
        "terminal.ansi.white": "#d0d8e5ff",
        "terminal.ansi.bright_white": "#f0f4f8ff",
        "terminal.ansi.dim_black": "#0f131acc",
        "terminal.ansi.dim_red": "#ff8595aa",
        "terminal.ansi.dim_green": "#b3f5d7aa",
        "terminal.ansi.dim_yellow": "#e0c78aaa",
        "terminal.ansi.dim_blue": "#4fc1e9aa",
        "terminal.ansi.dim_magenta": "#bda6ffaa",
        "terminal.ansi.dim_cyan": "#99e6ffaa",
        "terminal.ansi.dim_white": "#d0d8e5aa",

        "text": "#d0d8e5ff",
        "text.muted": "#9aafc5ff",
        "text.placeholder": "#8fa3b9ff",
        "text.disabled": "#5c6e83ff",
        "text.accent": "#99e6ffff",

        "icon": "#9aafc5ff",
        "icon.muted": "#8fa3b9ff",
        "icon.disabled": "#5c6e83ff",
        "icon.accent": "#99e6ffff",

        "status_bar.background": "#0f131aff",
        "title_bar.background": "#0f131aff",
        "title_bar.inactive_background": "#151c26ff",
        "tab_bar.background": "#0f131aff",
        "tab.active_background": "#151c26ff",
        "tab.inactive_background": "#0f131aff",
        "toolbar.background": "#0f131aff",

        "border": "#0a0d12ff",
        "border.variant": "#4fc1e966",
        "border.focused": "#99e6ffff",
        "border.selected": "#8b9eb0ff",
        "border.disabled": "#55667aff",
        "border.transparent": "#00000000",

        "pane.focused_border": "#99e6ffcc",
        "panel.focused_border": "#99e6ffcc",
        "pane_group.border": "#0a0d12ff",

        "element.background": "#151c2600",
        "element.hover": "#4fc1e91a",
        "element.active": "#4fc1e944",
        "element.selected": "#4fc1e933",
        "element.disabled": "#00000000",

        "ghost_element.background": "#00000000",
        "ghost_element.hover": "#4fc1e91a",
        "ghost_element.active": "#4fc1e944",
        "ghost_element.selected": "#4fc1e933",
        "ghost_element.disabled": "#00000000",

        "scrollbar.track.background": "#00000000",
        "scrollbar.track.border": "#00000000",
        "scrollbar.thumb.background": "#6b7f96cc",
        "scrollbar.thumb.hover_background": "#7a8fa5ff",
        "scrollbar.thumb.active_background": "#99e6ff66",

        "focus.border": "#99e6ffff",
        "focus.background": "#4fc1e91a",
        "focus.highlight": "#99e6ffff",

        "conflict": "#ff8595ff",
        "conflict.background": "#ff85951a",
        "conflict.border": "#ff8595ff",

        "created": "#b3f5d7ff",
        "created.background": "#b3f5d71a",
        "created.border": "#b3f5d7ff",

        "deleted": "#ff8595ff",
        "deleted.background": "#ff85951a",
        "deleted.border": "#ff8595ff",

        "modified": "#c7b0ffff",
        "modified.background": "#bda6ff1a",
        "modified.border": "#c7b0ffff",

        "renamed": "#99e6ffff",
        "renamed.background": "#99e6ff1a",
        "renamed.border": "#99e6ffff",

        "error": "#ff7b8bff",
        "error.background": "#ff7b8b1a",
        "error.border": "#ff7b8bff",

        "warning": "#e0c78aff",
        "warning.background": "#e0c78a1a",
        "warning.border": "#e0c78aff",

        "success": "#b3f5d7ff",
        "success.background": "#b3f5d71a",
        "success.border": "#b3f5d7ff",

        "info": "#4fc1e9ff",
        "info.background": "#4fc1e91a",
        "info.border": "#4fc1e9ff",

        "hint": "#9aafc5ff",
        "hint.background": "#4fc1e90f",
        "hint.border": "#9aafc566",

        "predictive": "#8fa3b9cc",
        "predictive.background": "#4fc1e90f",
        "predictive.border": "#8fa3b966",

        "ignored": "#5c6e83ff",
        "ignored.background": "#5c6e831a",
        "ignored.border": "#5c6e8344",

        "drop_target.background": "#4fc1e922",

        "search.match_background": "#4fc1e933",
        "search.active_match_background": "#e0c78acc",

        "link_text.hover": "#99e6ffff",

        "list.selection": "#4fc1e91a",
        "list.selection.border": "#4fc1e944",
        "list.highlight": "#4fc1e91a",
        "list.hover": "#4fc1e90f",
        "list.focus": "#4fc1e91a",

        "tooltip.background": "#1d2532ff",
        "tooltip.border": "#55667aff",
        "tooltip.text": "#d0d8e5ff",

        "dropdown.background": "#151c26ff",
        "dropdown.border": "#1d2532ff",
        "dropdown.list.background": "#1d2532ff",

        "checkbox.background": "#151c26ff",
        "checkbox.border": "#55667aff",
        "checkbox.checked.background": "#4fc1e9ff",
        "checkbox.checked.border": "#4fc1e9ff",

        "syntax": {
          "comment": { "color": "#7a8fa5ff", "font_style": "italic" },
          "comment.doc": { "color": "#7a8fa5ff", "font_style": "italic" },
          "keyword": { "color": "#bda6ffff" },
          "keyword.control": { "color": "#bda6ffff", "font_weight": 500 },
          "keyword.operator": { "color": "#4fc1e9cc" },
          "keyword.other.important": { "color": "#ff7b8bff" },
          "storage.modifier": { "color": "#bda6ffff" },
          "storage.type": { "color": "#c7b0ffff" },
          "constant": { "color": "#e0c78aff" },
          "constant.numeric": { "color": "#e0c78aff" },
          "constant.character": { "color": "#e0c78aff" },
          "constant.character.escape": { "color": "#e0c78aff" },
          "string": { "color": "#b3f5d7ff" },
          "string.escape": { "color": "#c5ffe3ff" },
          "string.regex": { "color": "#b3f5d7ff" },
          "string.special": { "color": "#c5ffe3ff" },
          "string.special.symbol": { "color": "#b3f5d7ff" },
          "text.literal": { "color": "#b3f5d7ff" },
          "variable": { "color": "#d0d8e5ff" },
          "variable.parameter": {
            "color": "#9aafc5ff",
            "font_style": "italic"
          },
          "variable.member": { "color": "#d0d8e5ff" },
          "variable.special": { "color": "#ff9eb5ff" },
          "property": { "color": "#99e6ffff" },
          "function": { "color": "#99e6ffff" },
          "function.method": { "color": "#7fd9ffff" },
          "function.special": { "color": "#8ad0ffff" },
          "support.function": { "color": "#8ad0ffff" },
          "support.type": { "color": "#6bcdf9ff" },
          "support.type.property-name": { "color": "#7fd9ffff" },
          "constructor": { "color": "#7fd9ffff" },
          "type": { "color": "#6bcdf9ff" },
          "type.enum": { "color": "#6bcdf9ff" },
          "type.interface": { "color": "#6bcdf9ff" },
          "type.struct": { "color": "#6bcdf9ff" },
          "entity.name.type": { "color": "#6bcdf9ff" },
          "entity.name.function": { "color": "#99e6ffff", "font_weight": 500 },
          "entity.name.tag": { "color": "#e0c78aff" },
          "entity.other.attribute-name": { "color": "#6bcdf9ff" },
          "attribute": { "color": "#6bcdf9ff" },
          "tag": { "color": "#e0c78aff" },
          "punctuation": { "color": "#8b9eb0ff" },
          "punctuation.bracket": { "color": "#8b9eb0ff" },
          "punctuation.delimiter": { "color": "#8b9eb0ff" },
          "punctuation.list_marker": { "color": "#4fc1e9ff" },
          "punctuation.special": { "color": "#ff9eb5ff" },
          "emphasis": { "color": "#bda6ffff", "font_style": "italic" },
          "title": { "color": "#99e6ffff", "font_weight": 700 },
          "markup.heading": { "color": "#bda6ffff", "font_weight": 600 },
          "markup.bold": { "color": "#e0c78aff", "font_weight": 700 },
          "markup.italic": { "color": "#99e6ffff", "font_style": "italic" },
          "markup.link": { "color": "#4fc1e9ff", "font_style": "normal" },
          "markup.raw": { "color": "#b3f5d7ff" },
          "markup.list": { "color": "#d0d8e5ff" },
          "markup.quote": { "color": "#9aafc5ff", "font_style": "italic" }
        },

        "players": [
          {
            "cursor": "#4fc1e9",
            "selection": "#4fc1e944",
            "background": "#4fc1e91a"
          },
          {
            "cursor": "#bda6ff",
            "selection": "#bda6ff44",
            "background": "#bda6ff1a"
          },
          {
            "cursor": "#ff9eb5",
            "selection": "#ff9eb544",
            "background": "#ff9eb51a"
          },
          {
            "cursor": "#b3f5d7",
            "selection": "#b3f5d744",
            "background": "#b3f5d71a"
          },
          {
            "cursor": "#e0c78a",
            "selection": "#e0c78a44",
            "background": "#e0c78a1a"
          },
          {
            "cursor": "#99e6ff",
            "selection": "#99e6ff44",
            "background": "#99e6ff1a"
          },
          {
            "cursor": "#8b9eb0",
            "selection": "#8b9eb044",
            "background": "#8b9eb01a"
          },
          {
            "cursor": "#d0d8e5",
            "selection": "#d0d8e544",
            "background": "#d0d8e51a"
          }
        ]
      }
    }
  ]
}
